tap_zendesk/__init__.py
tap_zendesk/discover.py
tap_zendesk/internal_config.json
tap_zendesk/metrics.py
tap_zendesk/streams.py
tap_zendesk/sync.py
tap_zendesk/schemas/group_memberships.json
tap_zendesk/schemas/groups.json
tap_zendesk/schemas/macros.json
tap_zendesk/schemas/organizations.json
tap_zendesk/schemas/satisfaction_ratings.json
tap_zendesk/schemas/sla_policies.json
tap_zendesk/schemas/tags.json
tap_zendesk/schemas/ticket_audits.json
tap_zendesk/schemas/ticket_comments.json
tap_zendesk/schemas/ticket_fields.json
tap_zendesk/schemas/ticket_forms.json
tap_zendesk/schemas/ticket_metrics.json
tap_zendesk/schemas/tickets.json
tap_zendesk/schemas/users.json
tap_zendesk/schemas/shared/attachments.json
tap_zendesk/schemas/shared/metadata.json
tap_zendesk/schemas/shared/via.json
tap_zendesk_parallel-1.4.11.dist-info/LICENSE
tap_zendesk_parallel-1.4.11.dist-info/METADATA
tap_zendesk_parallel-1.4.11.dist-info/WHEEL
tap_zendesk_parallel-1.4.11.dist-info/entry_points.txt
tap_zendesk_parallel-1.4.11.dist-info/top_level.txt
tap_zendesk_parallel-1.4.11.dist-info/RECORD
