Metadata-Version: 2.1
Name: tap-zendesk-parallel
Version: 1.4.11
Summary: Singer.io tap for extracting data from the Zendesk API
Home-page: https://singer.io
Author: Stitch
License: UNKNOWN
Platform: UNKNOWN
Classifier: Programming Language :: Python :: 3 :: Only
Requires-Dist: singer-python (==5.2.1)
Requires-Dist: zenpy (==2.0.0)
Provides-Extra: dev
Requires-Dist: ipdb ; extra == 'dev'
Requires-Dist: pylint ; extra == 'dev'
Requires-Dist: nose ; extra == 'dev'
Requires-Dist: nose-watch ; extra == 'dev'
